diced/lib.pyi
diced/lib.rs
diced/__init__.py
diced/py.typed
diced/lib.cpython-38-darwin.so
diced/tests/requirements.txt
diced/tests/__init__.py
diced/tests/unittest.rs
diced/tests/test_scan.py
diced/tests/test_doctest.py
diced/tests/data/Aquifex_aeolicus_VF5.fna
diced/tests/data/__init__.py
diced-0.1.2.dist-info/RECORD
diced-0.1.2.dist-info/WHEEL
diced-0.1.2.dist-info/METADATA
diced-0.1.2.dist-info/licenses/COPYING
