Metadata-Version: 2.3
Name: diced
Version: 0.1.2
Classifier: Development Status :: 3 - Alpha
Classifier: Intended Audience :: Developers
Classifier: Intended Audience :: Science/Research
Classifier: License :: OSI Approved :: GNU General Public License v3 or later (GPLv3+)
Classifier: Operating System :: OS Independent
Classifier: Programming Language :: Rust
Classifier: Programming Language :: Python :: 3.7
Classifier: Programming Language :: Python :: 3.8
Classifier: Programming Language :: Python :: 3.9
Classifier: Programming Language :: Python :: 3.10
Classifier: Programming Language :: Python :: 3.11
Classifier: Programming Language :: Python :: 3.12
Classifier: Programming Language :: Python :: 3.13
Classifier: Programming Language :: Python :: Implementation :: CPython
Classifier: Programming Language :: Python :: Implementation :: PyPy
Classifier: Topic :: Scientific/Engineering :: Bio-Informatics
Classifier: Topic :: Scientific/Engineering :: Medical Science Apps.
Classifier: Topic :: Software Development :: Libraries :: Python Modules
Classifier: Typing :: Typed
License-File: COPYING
Summary: Rust re-implementation of the MinCED algorithm to Detect Instances of CRISPRs in Environmental Data.
Keywords: bioinformatics,genomics,repeat,crispr
Home-Page: https://github.com/althonos/lightmotif/tree/main/diced-py
Author: Martin Larralde <martin.larralde@embl.de>
Author-email: Martin Larralde <martin.larralde@embl.de>
License: GPL-3.0-or-later
Requires-Python: >=3.7
Project-URL: Documentation, https://diced.readthedocs.io
Project-URL: Bug Tracker, https://github.com/althonos/diced/issues
Project-URL: Changelog, https://github.com/althonos/diced/blob/master/CHANGELOG.md
Project-URL: Coverage, https://codecov.io/gh/althonos/diced/
Project-URL: Builds, https://github.com/althonos/diced/actions/
Project-URL: PyPI, https://pypi.org/project/diced
